<?xml version="1.0" encoding="utf-8"?>
<!DOCTYPE hibernate-mapping PUBLIC "-//Hibernate/Hibernate Mapping DTD 3.0//EN"
"http://www.hibernate.org/dtd/hibernate-mapping-3.0.dtd">
<!-- 
    Mapping file autogenerated by MyEclipse Persistence Tools
-->
<hibernate-mapping>
    <class name="csdc.bean.SinossModifyContent" table="T_SINOSS_MODIFY_CONTENT">
        <id name="id" type="java.lang.String">
            <column name="C_ID" length="40"/>
            <generator class="uuid.hex"/>
        </id>
        <property name="modifyFieldMean" type="java.lang.String">
            <column name="C_modify_Field_Mean"/>
        </property>
        <property name="beforeValue" type="java.lang.String">
            <column name="C_before_Value"/>
        </property>
        <property name="afterValue" type="java.lang.String">
            <column name="C_after_Value"/>
        </property>
        <property name="idNumber" type="java.lang.String">
            <column name="C_id_Number"/>
        </property>
        <many-to-one name="projectVariation" class="csdc.bean.SinossProjectVariation" fetch="join">
            <column name="C_project_Variation_ID"/>
        </many-to-one>
        <property name="sinossId" type="java.lang.String">
			<column name="c_sinoss_Id" />
		</property>
    </class>
</hibernate-mapping>