<?xml version="1.0" encoding="utf-8"?>
<!DOCTYPE hibernate-mapping PUBLIC "-//Hibernate/Hibernate Mapping DTD 3.0//EN"
"http://www.hibernate.org/dtd/hibernate-mapping-3.0.dtd">
<!-- 
    Mapping file autogenerated by MyEclipse Persistence Tools
-->
<hibernate-mapping>
    <class name="csdc.bean.SinossChecklogs" table="T_SINOSS_CHECKLOGS">
        <id name="id" type="java.lang.String">
            <column name="C_ID" length="40"/>
            <generator class="uuid.hex"/>
        </id>
        <property name="checkStatus" type="java.lang.Integer">
            <column name="C_CHECK_status" precision="1" scale="0" not-null="true" />
        </property>
        <property name="type" type="java.lang.Integer">
            <column name="C_type" precision="1" scale="0" not-null="true" />
        </property>
        <property name="dumpDate" type="java.util.Date">
			<column name="C_DUMP_DATE" />
		</property>
        <property name="checkDate" type="java.util.Date">
            <column name="C_check_Date"/>
        </property>
        <property name="checker" type="java.lang.String">
            <column name="C_checker"/>
        </property>
        <property name="isAdded" type="java.lang.Integer">
            <column name="C_IS_ADDED"/>
        </property>
        <property name="checkInfo" type="java.lang.String">
            <column name="C_check_Info"/>
        </property>
        <many-to-one name="projectVariation" class="csdc.bean.SinossProjectVariation" fetch="join">
            <column name="C_project_Variation_ID"/>
        </many-to-one>
        <many-to-one name="projectMidinspection" class="csdc.bean.SinossProjectMidinspection" fetch="join">
            <column name="C_project_Midinspection_ID"/>
        </many-to-one>
        <many-to-one name="projectApplication" class="csdc.bean.SinossProjectApplication" fetch="join">
            <column name="C_project_Application_ID"/>
        </many-to-one>
        <many-to-one name="projectEndinspection" class="csdc.bean.SinossProjectEndinspection" fetch="join">
            <column name="C_project_Endinspection_ID"/>
        </many-to-one>
        <property name="sinossId" type="java.lang.String">
			<column name="c_sinoss_Id" />
		</property>
		<property name="sinossProjectId" type="java.lang.String">
			<column name="C_SINOSS_PROJECT_ID" />
		</property>
    </class>
</hibernate-mapping>