<?xml version="1.0" encoding="UTF-8"?>

<!DOCTYPE struts PUBLIC "-//Apache Software Foundation//DTD Struts Configuration 2.0//EN" "http://struts.apache.org/dtds/struts-2.0.dtd">

<struts>
	<package name="OtherProduct" extends="main" namespace="/product/otherProduct">
	
		<action name="toList" class="OtherProductAction" method="toList">
			<result>/product/otherProduct/list.jsp</result>
		</action>

		<action name="list" class="OtherProductAction" method="list">
			<result type="json"><param name="root">jsonMap</param></result>
			<result name="input" type="json"><param name="root">jsonMap</param></result>
		</action>

		<action name="simpleSearch" class="OtherProductAction" method="simpleSearch">
			<result type="chain">list</result>
		</action>

		<action name="advSearch" class="OtherProductAction" method="advSearch">
			<result type="chain">list</result>
		</action>
		
		<action name="sort" class="OtherProductAction" method="sort">
			<result type="chain">list</result>
		</action>

		<action name="changePageSize" class="OtherProductAction" method="changePageSize">
			<result type="chain">list</result>
		</action>

		<action name="toPage" class="OtherProductAction" method="toPage">
			<result type="chain">list</result>
		</action>
		
		<action name="toAdd" class="OtherProductAction" method="toAdd">
			<result>/product/otherProduct/add.jsp</result>
		</action>
		
    	<action name="add" class="OtherProductAction" method="add"> 
       		<param name="savePath">/upload/product/otherProduct</param>
       		<result type="redirectAction">
				<param name="entityId">${entityId}</param>
				<param name="productflag">${productflag}</param>
				<param name="actionName">toView</param>	
	        </result>
	        <result name="finish" type="json"><param name="root">jsonMap</param></result>
<!--       		<result name="finish">/product/extIf/popAdd.jsp</result>-->
        	<result name="input">${inputView}</result>
    	</action>
    		  	 
	 	<action name="toModify" class="OtherProductAction" method="toModify">
	    	<result>/product/otherProduct/modify.jsp</result>
	    	<result name="finish">/product/extIf/popModifyOtherProduct.jsp</result>
	   	</action>
	   	
	 	<action name="modify" class="OtherProductAction" method="modify">
 	    	<param name="savePath">/upload/product/otherProduct</param>
 	    	<result type="redirectAction">
		 		<param name="entityId">${entityId}</param>
				<param name="productflag">${productflag}</param>
				<param name="update">1</param>
			 	<param name="actionName">toView</param>	
	      	</result>
	      	<result name="finish" type="json"><param name="root">jsonMap</param></result>
      		<result name="input">/product/otherProduct/modify.jsp</result>
	   	</action>
	   	
		<action name="delete" class="OtherProductAction" method="delete">
			<result type="json"><param name="root">jsonMap</param></result>
			<result name="input" type="json"><param name="root">jsonMap</param></result>
		</action>
		
		<action name="toView" class="OtherProductAction" method="toView">
			<result>/product/otherProduct/view.jsp</result>
			<result name="popView">/product/extIf/popViewOtherProduct.jsp</result>
		</action>
		
		<action name="view" class="OtherProductAction" method="view">
			<result type="json"><param name="root">jsonMap</param></result>
		</action>
		
		<action name="prev" class="OtherProductAction" method="prev">
			<result type="redirectAction">
				<param name="actionName">view</param>
				<param name="entityId">${entityId}</param>
			</result>
			<result name="input" type="json"><param name="root">jsonMap</param></result>
		</action>
		
		<action name="next" class="OtherProductAction" method="next">
			<result type="redirectAction">
				<param name="actionName">view</param>
				<param name="entityId">${entityId}</param>
			</result>
			<result name="input" type="json"><param name="root">jsonMap</param></result>
		</action>
		
		<action name="toAudit" class="OtherProductAction" method="toAudit">
			<result>/product/popAudit.jsp</result>
		</action>
		
		<action name="audit" class="OtherProductAction" method="audit">
			<result type="json"><param name="root">jsonMap</param></result>
			<result name="input" type="json"><param name="root">jsonMap</param></result>
		</action>
		
		<action name="viewAudit" class="OtherProductAction" method="viewAudit">
			<result>/product/popViewAudit.jsp</result>
		</action>
	
		<action name="toAddApply" class="OtherProductAction" method="toAddApply">
			<result>/product/popAddApply.jsp</result>
		</action>
		
		<action name="toModifyApply" class="OtherProductAction" method="toModifyApply">
			<result>/product/popModifyApply.jsp</result>
		</action>
		
	    <action name="download" class="OtherProductAction" method="download">
      		<result type="stream">   		 
 				<param name="inputName">targetFile</param> 
 				<param name="bufferSize">4096</param>
 				<param name="contentType">application/octet-stream</param>
	 			<param name="contentDisposition">attachment;fileName="${fileFileName}"</param>  
	 		</result>
	 	</action>
	 	
	   	<action name="validateFile" class="OtherProductAction" method="validateFile">
   			<result type="json"><param name="root">jsonMap</param></result>
	   		<result type="json" name="input"><param name="root">jsonMap</param></result>	
	  	 </action>

	   	<action name="exAdd" class="OtherProductAction" method="exAdd">
   			<result type="json"><param name="root">jsonMap</param></result>
	   		<result type="json" name="input"><param name="root">jsonMap</param></result>	
	   	</action>
	   	
	</package>
</struts>